scheme/Globals.py
scheme/begin.py
scheme/case.py
scheme/cond.py
scheme/interfaces.py
scheme/let_aster.py
scheme/quasiquote.py
scheme/quasisyntax.py
scheme/quote.py
scheme/syntax.py
scheme/syntax_case.py
scheme/token.py
scheme/unquote.py
scheme/unquote_splicing.py
scheme/IF.py
scheme/PatternMatcher.py
scheme/let.py
scheme/parser.py
scheme/syntax_rules.py
scheme/processer.py
scheme/utils.py
scheme/define_syntax.py
scheme/eval.py
scheme/define.py
scheme/Lambda.py
scheme/environment.py
scheme/builtins.py
scheme/debug.py
scheme/callcc.py
scheme/macro.py
scheme/repl.py
scheme/syntax_expand.py
scheme/symbol.py
scheme/__init__.py
scheme/procedure.py
scheme/jit.py
SchemePy-1.2.0.data/data/share/schemepy/stdlib/let-syntax.scm
SchemePy-1.2.0.data/data/share/schemepy/stdlib/letrec.scm
SchemePy-1.2.0.data/data/share/schemepy/stdlib/print.scm
SchemePy-1.2.0.data/data/share/schemepy/stdlib/and.scm
SchemePy-1.2.0.data/data/share/schemepy/stdlib/newline.scm
SchemePy-1.2.0.data/data/share/schemepy/stdlib/for.scm
SchemePy-1.2.0.data/data/share/schemepy/stdlib/apply.scm
SchemePy-1.2.0.data/data/share/schemepy/stdlib/let.scm
SchemePy-1.2.0.data/scripts/schemepy
SchemePy-1.2.0.dist-info/top_level.txt
SchemePy-1.2.0.dist-info/METADATA
SchemePy-1.2.0.dist-info/DESCRIPTION.rst
SchemePy-1.2.0.dist-info/metadata.json
SchemePy-1.2.0.dist-info/WHEEL
SchemePy-1.2.0.dist-info/RECORD
