Metadata-Version: 2.0
Name: SchemePy
Version: 1.2.0
Summary: R5RS scheme interpreter, supporting hygenic macros and full call/cc
Home-page: https://github.com/perkinslr/schemepy
Author: Logan Perkins
Author-email: perkins@injeanieousdesigns.com
License: LGPL
Keywords: scheme r5rs define-syntax call/cc
Platform: UNKNOWN
Requires: zope.interface
